focustui/__init__.py
focustui/__main__.py
focustui/app.py
focustui/assets.py
focustui/config_manager.py
focustui/constants.py
focustui/db.py
focustui/setup.py
focustui/sound_file_manager.py
focustui/sound_manager.py
focustui/style.tcss
focustui/validators.py
focustui/composite_widgets/__init__.py
focustui/composite_widgets/about_settings.py
focustui/composite_widgets/clock_display.py
focustui/composite_widgets/sound_settings.py
focustui/modals/__init__.py
focustui/modals/add_sound_tree.py
focustui/modals/confirmation_popup.py
focustui/modals/edit_sound.py
focustui/screens/__init__.py
focustui/screens/focus_screen.py
focustui/screens/settings_screen.py
focustui/static/sounds/longs/Woodpecker_Forest.flac
focustui/static/sounds/shorts/Acid_Bassline.flac
focustui/static/sounds/shorts/Braam.flac
focustui/static/sounds/shorts/Landing_Forcefield.flac
focustui/static/sounds/shorts/Woohoo.flac
focustui/utils/__init__.py
focustui/utils/parsers.py
focustui/widgets/__init__.py
focustui/widgets/accordion.py
focustui/widgets/inputs.py
focustui/widgets/music_directory_tree.py
focustui-0.1.20.dist-info/METADATA
focustui-0.1.20.dist-info/WHEEL
focustui-0.1.20.dist-info/entry_points.txt
focustui-0.1.20.dist-info/licenses/LICENSE
focustui-0.1.20.dist-info/RECORD
