Metadata-Version: 2.3
Name: focustui
Version: 0.1.20
Summary: Your Deep Focus Session Buddy.
Project-URL: Homepage, https://github.com/Zimzozaur/focus-tui
Project-URL: Issues, https://github.com/Zimzozaur/focus-tui/issues
Author-email: Simon Piechutowski <szymonpiechutowski@gmail.com>
License-File: LICENSE
Classifier: Development Status :: 3 - Alpha
Classifier: Environment :: Console
Classifier: Intended Audience :: End Users/Desktop
Classifier: License :: OSI Approved :: MIT License
Classifier: Operating System :: MacOS
Classifier: Operating System :: Microsoft :: Windows :: Windows 10
Classifier: Operating System :: Microsoft :: Windows :: Windows 11
Classifier: Operating System :: POSIX :: Linux
Classifier: Programming Language :: Python
Classifier: Programming Language :: Python :: 3.12
Classifier: Topic :: Education
Classifier: Topic :: Office/Business :: Scheduling
Classifier: Topic :: Terminals
Classifier: Topic :: Utilities
Requires-Python: >=3.12
Requires-Dist: click~=8.1.7
Requires-Dist: platformdirs~=4.2.2
Requires-Dist: pydantic<3.0.0,>=2.8.2
Requires-Dist: pygame-ce~=2.5.0
Requires-Dist: python-dotenv~=1.0.1
Requires-Dist: textual>=0.73.0
Provides-Extra: dev
Requires-Dist: pre-commit~=4.0.1; extra == 'dev'
Requires-Dist: pytest-asyncio~=0.24.0; extra == 'dev'
Requires-Dist: pytest-env~=1.1.3; extra == 'dev'
Requires-Dist: pytest-mock~=3.14.0; extra == 'dev'
Requires-Dist: pytest~=8.3.2; extra == 'dev'
Requires-Dist: ruff>=0.6.1; extra == 'dev'
Requires-Dist: textual-dev~=1.5.1; extra == 'dev'
